{
  "id": "github_issues_8c7123ad18ef",
  "source": "github_issues",
  "source_url": "https://github.com/MigoXLab/webqa-agent/issues/144",
  "license": null,
  "retrieved_at": "2026-07-15T04:16:48.210646+00:00",
  "retrieval_method": "gh_cli",
  "content": {
    "query": "AI generated code bug",
    "repo": null,
    "title": "[AINAScan] 3 security/quality issues detected",
    "state": "open",
    "labels": [],
    "excerpt": "## 🔍 AINAScan Automated Security Report\n\n> This report was generated automatically by [AINAScan](https://pleasing-transformation-production-90c2.up.railway.app) — a deterministic AST-based scanner for AI-generated code bugs.\n> Feel free to close this issue if not applicable.\n\n**Repository:** `MigoXLab/webqa-agent`  \n**Scan date:** 2026-06-25  \n**Issues found:** 3 BLOCK-level  \n\n---\n\n## Issues\n\n### 1. `PATH_TRAVERSAL` — `backend/gen_webqa.py` (line 40)\n**🧠 98% confidence · L3×4**\n\n> open() with p"
  },
  "content_hash": "8c7123ad18ef2f4aff8fd10cbb27fdfd1735a7640906d361be8ad28502a95000",
  "feeds_topics": [
    "T4",
    "T6"
  ],
  "validation": {
    "status": "valid",
    "reasons": []
  },
  "classification": null
}